[
    {
      "Prime": false,
      "Distance": 0.0,
      "UnitNumber": 2110,
      "AddressLine1": "66 Third Ave (11th St.)",
      "AddressLine2": null,
      "City": "New York",
      "Latitude": 40.7314380000,
      "Longitude": -73.9887010000,
      "PostalCode": "10003",
      "State": "NY",
      "StateName": "New York",  
      "TheatreName": "AMC Loews Village 7",
      "LongName": "AMC Loews Village 7",
      "PhoneNumber": "888-AMC-4FUN",
      "GuestServicesPhoneNumber": "2129822116",
      "WebsiteUrl": "/movie-theatres/amc-loews-village-7",
      "TheatreImageStandardUrl": "https://cdn.amctheatres.com/theatres/images/Primary/Standard/fallback-2.jpg",
      "TheatreImageThumbUrl": "https://cdn.amctheatres.com/theatres/images/Primary/Thumb/fallback-2.jpg",
      "TheatreImageIconUrl": "https://cdn.amctheatres.com/theatres/images/StoreIcon/Thumb/fallback-2.jpg",
      "IMAX": false,
      "CinemaSuites": false,
      "ForkAndScreen": false,
      "ThreeD": true,
      "ETX": false,
      "AMCIndependent": true,
      "TheatreAddress": "66 Third Ave (11th St.), New York, NY 10003",
      "OnlineTicketSales": "AMC"
    },
    {
      "Prime": false,
      "Distance": 0.5,
      "UnitNumber": 2112,
      "AddressLine1": "890 Broadway",
      "AddressLine2": null,
      "City": "New York",
      "Latitude": 40.7385120000,
      "Longitude": -73.9898370000,
      "PostalCode": "10003",
      "State": "NY",
      "StateName": "New York",
      "TheatreName": "AMC Loews 19th St. East 6",
      "LongName": "AMC Loews 19th St. East 6",
      "PhoneNumber": "888-AMC-4FUN",
      "GuestServicesPhoneNumber": "2122608173",
      "WebsiteUrl": "/movie-theatres/amc-loews-19th-st-east-6",
      "TheatreImageStandardUrl": "https://cdn.amctheatres.com/theatres/images/Primary/Standard/fallback-2.jpg",
      "TheatreImageThumbUrl": "https://cdn.amctheatres.com/theatres/images/Primary/Thumb/fallback-2.jpg",
      "TheatreImageIconUrl": "https://cdn.amctheatres.com/theatres/images/StoreIcon/Thumb/fallback-2.jpg",
      "IMAX": false,
      "CinemaSuites": false,
      "ForkAndScreen": false,
      "ThreeD": true,
      "ETX": false,
      "AMCIndependent": true,
      "TheatreAddress": "890 Broadway, New York, NY 10003",
      "OnlineTicketSales": "AMC"
    },
    {
      "Prime": false,
      "Distance": 1.0,
      "UnitNumber": 2195,
      "AddressLine1": "570 Second Avenue",
      "AddressLine2": null,
      "City": "New York",
      "Latitude": 40.7428920000,
      "Longitude": -73.9769140000,
      "PostalCode": "10016",
      "State": "NY",
      "StateName": "New York",
      "TheatreName": "AMC Loews Kips Bay 15",
      "LongName": "AMC Loews Kips Bay 15",
      "PhoneNumber": "888-AMC-4FUN",
      "GuestServicesPhoneNumber": "2124470638",
      "WebsiteUrl": "/movie-theatres/amc-loews-kips-bay-15",
      "TheatreImageStandardUrl": "https://cdn.amctheatres.com/theatres/images/Primary/Standard/2195.jpg",
      "TheatreImageThumbUrl": "https://cdn.amctheatres.com/theatres/images/Primary/Thumb/2195.jpg",
      "TheatreImageIconUrl": "https://cdn.amctheatres.com/theatres/images/StoreIcon/Thumb/fallback-2.jpg",
      "IMAX": true,
      "CinemaSuites": false,
      "ForkAndScreen": false,
      "ThreeD": true,
      "ETX": false,
      "AMCIndependent": true,
      "TheatreAddress": "570 Second Avenue, New York, NY 10016",
      "OnlineTicketSales": "AMC"
    },
    {
      "Prime": false,
      "Distance": 1.5,
      "UnitNumber": 2120,
      "AddressLine1": "312 West 34th Street",
      "AddressLine2": null,
      "City": "New York",
      "Latitude": 40.7524440000,
      "Longitude": -73.9943900000,
      "PostalCode": "10001",
      "State": "NY",
      "StateName": "New York",
      "TheatreName": "AMC Loews 34th Street 14",
      "LongName": "AMC Loews 34th Street 14",
      "PhoneNumber": "888-AMC-4FUN",
      "GuestServicesPhoneNumber": "2122444556",
      "WebsiteUrl": "/movie-theatres/amc-loews-34th-street-14",
      "TheatreImageStandardUrl": "https://cdn.amctheatres.com/theatres/images/Primary/Standard/2120.jpg",
      "TheatreImageThumbUrl": "https://cdn.amctheatres.com/theatres/images/Primary/Thumb/2120.jpg",
      "TheatreImageIconUrl": "https://cdn.amctheatres.com/theatres/images/StoreIcon/Thumb/fallback-1.jpg",
      "IMAX": true,
      "CinemaSuites": false,
      "ForkAndScreen": false,
      "ThreeD": true,
      "ETX": false,
      "AMCIndependent": false,
      "TheatreAddress": "312 West 34th Street, New York, NY 10001",
      "OnlineTicketSales": "AMC"
    },
    {
      "Prime": false,
      "Distance": 1.8,
      "UnitNumber": 552,
      "AddressLine1": "234 West 42nd Street",
      "AddressLine2": null,
      "City": "New York",
      "Latitude": 40.7568410000,
      "Longitude": -73.9891390000,
      "PostalCode": "100360000",
      "State": "NY",
      "StateName": "New York",
      "TheatreName": "AMC Empire 25",
      "LongName": "AMC Empire 25",
      "PhoneNumber": "888-AMC-4FUN",
      "GuestServicesPhoneNumber": "2123982597",
      "WebsiteUrl": "/movie-theatres/amc-empire-25",
      "TheatreImageStandardUrl": "https://cdn.amctheatres.com/theatres/images/Primary/Standard/552.jpg",
      "TheatreImageThumbUrl": "https://cdn.amctheatres.com/theatres/images/Primary/Thumb/552.jpg",
      "TheatreImageIconUrl": "https://cdn.amctheatres.com/theatres/images/StoreIcon/Thumb/552.jpg",
      "IMAX": true,
      "CinemaSuites": false,
      "ForkAndScreen": false,
      "ThreeD": true,
      "ETX": true,
      "AMCIndependent": true,
      "TheatreAddress": "234 West 42nd Street, New York, NY 10036",
      "OnlineTicketSales": "AMC"
    },
    {
      "Prime": false,
      "Distance": 2.6,
      "UnitNumber": 2184,
      "AddressLine1": "30-300 Mall Drive West",
      "AddressLine2": null,
      "City": "Jersey City",
      "Latitude": 40.7270580000,
      "Longitude": -74.0386400000,
      "PostalCode": "07303",
      "State": "NJ",
      "StateName": "New Jersey",
      "TheatreName": "AMC Loews Newport Centre 11",
      "LongName": "AMC Loews Newport Centre 11",
      "PhoneNumber": "888-AMC-4FUN",
      "GuestServicesPhoneNumber": "2016263258",
      "WebsiteUrl": "/movie-theatres/amc-loews-newport-centre-11",
      "TheatreImageStandardUrl": "https://cdn.amctheatres.com/theatres/images/Primary/Standard/2184.jpg",
      "TheatreImageThumbUrl": "https://cdn.amctheatres.com/theatres/images/Primary/Thumb/2184.jpg",
      "TheatreImageIconUrl": "https://cdn.amctheatres.com/theatres/images/StoreIcon/Thumb/fallback-3.jpg",
      "IMAX": false,
      "CinemaSuites": false,
      "ForkAndScreen": false,
      "ThreeD": true,
      "ETX": false,
      "AMCIndependent": false,
      "TheatreAddress": "30-300 Mall Drive West, Jersey City, NJ 07303",
      "OnlineTicketSales": "AMC"
    },
    {
      "Prime": false,
      "Distance": 3.1,
      "UnitNumber": 2116,
      "AddressLine1": "1998 Broadway",
      "AddressLine2": null,
      "City": "New York",
      "Latitude": 40.7753030000,
      "Longitude": -73.9819440000,
      "PostalCode": "10023",
      "State": "NY",
      "StateName": "New York",
      "TheatreName": "AMC Loews Lincoln Square 13",
      "LongName": "AMC Loews Lincoln Square 13",
      "PhoneNumber": "888-AMC-4FUN",
      "GuestServicesPhoneNumber": "2123365020",
      "WebsiteUrl": "/movie-theatres/amc-loews-lincoln-square-13",
      "TheatreImageStandardUrl": "https://cdn.amctheatres.com/theatres/images/Primary/Standard/2116.jpg",
      "TheatreImageThumbUrl": "https://cdn.amctheatres.com/theatres/images/Primary/Thumb/2116.jpg",
      "TheatreImageIconUrl": "https://cdn.amctheatres.com/theatres/images/StoreIcon/Thumb/2116.jpg",
      "IMAX": true,
      "CinemaSuites": false,
      "ForkAndScreen": false,
      "ThreeD": true,
      "ETX": false,
      "AMCIndependent": true,
      "TheatreAddress": "1998 Broadway, New York, NY 10023",
      "OnlineTicketSales": "AMC"
    },
    {
      "Prime": false,
      "Distance": 3.8,
      "UnitNumber": 2104,
      "AddressLine1": "1538 Third Ave (86th St.)",
      "AddressLine2": null,
      "City": "New York",
      "Latitude": 40.7793090000,
      "Longitude": -73.9537850000,
      "PostalCode": "10028",
      "State": "NY",
      "StateName": "New York",
      "TheatreName": "AMC Loews Orpheum 7",
      "LongName": "AMC Loews Orpheum 7",
      "PhoneNumber": "888-AMC-4FUN",
      "GuestServicesPhoneNumber": "2128762111",
      "WebsiteUrl": "/movie-theatres/amc-loews-orpheum-7",
      "TheatreImageStandardUrl": "https://cdn.amctheatres.com/theatres/images/Primary/Standard/fallback-1.jpg",
      "TheatreImageThumbUrl": "https://cdn.amctheatres.com/theatres/images/Primary/Thumb/fallback-1.jpg",
      "TheatreImageIconUrl": "https://cdn.amctheatres.com/theatres/images/StoreIcon/Thumb/fallback-1.jpg",
      "IMAX": false,
      "CinemaSuites": false,
      "ForkAndScreen": false,
      "ThreeD": true,
      "ETX": false,
      "AMCIndependent": false,
      "TheatreAddress": "1538 Third Ave (86th St.), New York, NY 10028",
      "OnlineTicketSales": "AMC"
    },
    {
      "Prime": false,
      "Distance": 3.9,
      "UnitNumber": 2102,
      "AddressLine1": "2310 Broadway",
      "AddressLine2": null,
      "City": "New York",
      "Latitude": 40.7867130000,
      "Longitude": -73.9775510000,
      "PostalCode": "10024",
      "State": "NY",
      "StateName": "New York",
      "TheatreName": "AMC 84th Street 6",
      "LongName": "AMC 84th Street 6",
      "PhoneNumber": "888-AMC-4FUN",
      "GuestServicesPhoneNumber": "2127216023",
      "WebsiteUrl": "/movie-theatres/amc-84th-street-6",
      "TheatreImageStandardUrl": "https://cdn.amctheatres.com/theatres/images/Primary/Standard/534_now-reclining_C09F.jpg",
      "TheatreImageThumbUrl": "https://cdn.amctheatres.com/theatres/images/Primary/Thumb/534_now-reclining_7DBE.jpg",
      "TheatreImageIconUrl": "https://cdn.amctheatres.com/theatres/images/StoreIcon/Thumb/706_reclining_5F93.jpg",
      "IMAX": false,
      "CinemaSuites": false,
      "ForkAndScreen": false,
      "ThreeD": true,
      "ETX": false,
      "AMCIndependent": false,
      "TheatreAddress": "2310 Broadway, New York, NY 10024",
      "OnlineTicketSales": "AMC"
    },
    {
      "Prime": false,
      "Distance": 5.7,
      "UnitNumber": 2304,
      "AddressLine1": "2309 Frederick Douglas Blvd.",
      "AddressLine2": null,
      "City": "New York",
      "Latitude": 40.8095900000,
      "Longitude": -73.9517410000,
      "PostalCode": "10027",
      "State": "NY",
      "StateName": "New York",
      "TheatreName": "AMC Magic Johnson Harlem 9",
      "LongName": "AMC Magic Johnson Harlem 9",
      "PhoneNumber": "888-AMC-4FUN",
      "GuestServicesPhoneNumber": "2126656923",
      "WebsiteUrl": "/movie-theatres/amc-magic-johnson-harlem-9",
      "TheatreImageStandardUrl": "https://cdn.amctheatres.com/theatres/images/Primary/Standard/fallback-1.jpg",
      "TheatreImageThumbUrl": "https://cdn.amctheatres.com/theatres/images/Primary/Thumb/fallback-1.jpg",
      "TheatreImageIconUrl": "https://cdn.amctheatres.com/theatres/images/StoreIcon/Thumb/fallback-1.jpg",
      "IMAX": false,
      "CinemaSuites": false,
      "ForkAndScreen": false,
      "ThreeD": true,
      "ETX": false,
      "AMCIndependent": false,
      "TheatreAddress": "2309 Frederick Douglas Blvd., New York, NY 10027",
      "OnlineTicketSales": "AMC"
    }
]